relics_run_api/__init__.py
relics_run_api/base.py
relics_run_api/common.py
relics_run_api/history.py
relics_run_api/index.py
relics_run_api/market_data.py
relics_run_api/output.py
relics_run_api-0.1.1.dist-info/LICENSE
relics_run_api-0.1.1.dist-info/METADATA
relics_run_api-0.1.1.dist-info/WHEEL
relics_run_api-0.1.1.dist-info/RECORD
