Metadata-Version: 2.1
Name: relics-run-api
Version: 0.1.1
Summary: API for the Relics Run website.
License: GPL-3.0-or-later
Author: sehnryr
Author-email: youn@melois.dev
Requires-Python: >=3.11,<4.0
Classifier: License :: OSI Approved :: GNU General Public License v3 or later (GPLv3+)
Classifier: Programming Language :: Python :: 3
Classifier: Programming Language :: Python :: 3.11
Requires-Dist: requests (>=2.31.0,<3.0.0)
